{
	"configurations" : 
	[
		{
			"directories" : 
			[
				{
					"build" : ".",
					"hasInstallRule" : true,
					"jsonFile" : "directory-.-Debug-4471b9ae3efd97b9f02f.json",
					"minimumCMakeVersion" : 
					{
						"string" : "3.8"
					},
					"projectIndex" : 0,
					"source" : ".",
					"targetIndexes" : 
					[
						0,
						1
					]
				}
			],
			"name" : "Debug",
			"projects" : 
			[
				{
					"directoryIndexes" : 
					[
						0
					],
					"name" : "f1tenth_planner",
					"targetIndexes" : 
					[
						0,
						1
					]
				}
			],
			"targets" : 
			[
				{
					"directoryIndex" : 0,
					"id" : "gen_spline::@6890427a1f51a3e7e1df",
					"jsonFile" : "target-gen_spline-Debug-9400a5269ed40f59f8c0.json",
					"name" : "gen_spline",
					"projectIndex" : 0
				},
				{
					"directoryIndex" : 0,
					"id" : "main::@6890427a1f51a3e7e1df",
					"jsonFile" : "target-main-Debug-2d95c3d1f2cece81a60a.json",
					"name" : "main",
					"projectIndex" : 0
				}
			]
		}
	],
	"kind" : "codemodel",
	"paths" : 
	{
		"build" : "/home/jimin1203/misys/f1tenth_planner/build",
		"source" : "/home/jimin1203/misys/f1tenth_planner"
	},
	"version" : 
	{
		"major" : 2,
		"minor" : 3
	}
}
